codemodpydanticv1/__init__.py
codemodpydanticv1/cli.py
codemodpydanticv1/codemodpydanticv1.py
codemodpydanticv1-0.1.15.dist-info/METADATA
codemodpydanticv1-0.1.15.dist-info/WHEEL
codemodpydanticv1-0.1.15.dist-info/entry_points.txt
codemodpydanticv1-0.1.15.dist-info/RECORD
