Metadata-Version: 2.1
Name: codemodpydanticv1
Version: 0.1.15
Summary: 
Author: Your Name
Author-email: you@example.com
Requires-Python: >=3.10,<4.0
Classifier: Programming Language :: Python :: 3
Classifier: Programming Language :: Python :: 3.10
Classifier: Programming Language :: Python :: 3.11
Requires-Dist: libcst (>=1.1.0,<2.0.0)
Requires-Dist: typer (>=0.9.0,<0.10.0)
